{
  "tipo": "Tipo",
  "quantity": "Conteo de CFDIs",
  "empleados_qty": "Número de empleados",
  "total_percepciones": "Percepciones",
  "total_deducciones": "Deducciones",
  "otros_pagos": "Otros pagos",
  "PercepcionesTotalSueldos": "Sueldo",
  "otras_percepciones": "Otras percepciones",
  "separacion_indemnizacion": "Separación-Indemnización",
  "jubilacion_pension": "Jubilación-Pensión",
  "gravado": "Gravado",
  "exento": "Exento",
  "isr_retenido": "ISR retenido",
  "ajuste_isr_retenido": "Ajuste ISR retenido",
  "otras_deducciones": "Otras deducciones",
  "subsidio_causado": "Subsidio causado",
  "neto_a_pagar": "Neto a pagar"
}
